server.py
mcp_jira_forme-0.1.0.dist-info/METADATA
mcp_jira_forme-0.1.0.dist-info/WHEEL
mcp_jira_forme-0.1.0.dist-info/entry_points.txt
mcp_jira_forme-0.1.0.dist-info/top_level.txt
mcp_jira_forme-0.1.0.dist-info/RECORD
