Metadata-Version: 2.4
Name: mcp-jira-forme
Version: 0.1.0
Summary: Jira MCP Server
Requires-Python: >=3.10
Requires-Dist: fastmcp
Requires-Dist: atlassian-python-api
